{
  "Bookcase_Menu": "Quale libro leggi?",
  "Bookcase_Basics": "Le basi",
  "Bookcase_MakingFriends": "Fare amicizia",
  "Bookcase_Improvements": "Migliorie",
  "TV_Menu": "Seleziona che programma guardare:",
  "TV_Weather": "Meteo",
  "AncientFruitPot": "Le sue radici crescono a fondo... non sarebbe contenta lì dentro.",
  "TV_Fortune": "Oroscopo",
  "CaskNoCellar": "Funziona solo in cantina.",
  "DarkTalisman": "Talismano oscuro",
  "MagicInk": "Inchiostro magico",
  "MagnifyingGlass": "Lente d'ingrandimento",
  "BearPaw": "Sapienza dell'orso",
  "SpringOnionBugs": "Maestria con le cipolle primaverili",
  "SpecialCharm": "Amuleto speciale",
  "CatalogueDescription": "Fornisce accesso illimitato a tutti i pavimenti e le carte da parati... stando comodamente a casa!",
  "FurnitureCatalogueDescription": "Fornisce accesso illimitato a quasi tutti i mobili... stando comodamente a casa!",
  "DarkTalismanDescription": "Hai trovato il {0}! È coperto di melma d'insetto...",
  "MagicInkDescription": "Hai trovato l'{0} perduto dal Mago! Meglio riportarglielo.",
  "MagnifyingGlassDescription": "Hai ricevuto la {0}! Ora potrai trovare i 'Messaggi segreti'. Questi messaggi rivelano informazioni rare ed utili, e possono essere riletti nella sezione collezioni.",
  "SpecialCharmDescription": "Hai ricevuto l'{0}! Percepisci un'aura di buona sorte che ti circonda (fortuna permanentemente aumentata)!",
  "ParsnipSeedPackage_SomeoneElse": "Questo pacco appartiene a qualcun altro."
}