[
  {
    "NPCName": "Penny",
    "Reactions": [
      {
        "Tag": "*",
        "Response": "love",
        "Whitelist": [
          "Pam"
        ],
        "SpecialResponses": {
          "BeforeMovie": {
            "ResponsePoint": null,
            "Script": "",
            "Text": "ママと一緒に映画を見ると、確実に私は戻ります！"
          },
          "DuringMovie": {
            "ResponsePoint": null,
            "Script": "/message \"（パムとペニーは情熱を持って見てます！）」",
            "Text": ""
          },
          "AfterMovie": {
            "ResponsePoint": null,
            "Script": "",
            "Text": "家族でできることがもう一度できてうれしい！"
          }
        },
        "ID": "reaction_0"
      },
      {
        "Tag": "spring_movie_0",
        "Response": "love",
        "Whitelist": [],
        "SpecialResponses": {
          "BeforeMovie": {
            "ResponsePoint": null,
            "Script": "",
            "Text": "私はこれを楽しみにしています！ジャスとヴィンセントはそれについてストップしないで話しています。"
          },
          "DuringMovie": {
            "ResponsePoint": "sprout_leave",
            "Script": "/shake Penny 3000/pause 500/message \"ペニーは涙をこらえているようです...」",
            "Text": "うわー、そのように彼の家族を残すことはとても困難なはずです...$s"
          },
          "AfterMovie": {
            "ResponsePoint": null,
            "Script": "",
            "Text": "ここまで私を連れて来てくれてありがとう、そのことがどれほど良かったか、子供たちに話すのを待てません！"
          }
        },
        "ID": "reaction_1"
      },
      {
        "Tag": "spring_movie_0",
        "Response": "love",
        "Whitelist": [],
        "SpecialResponses": null,
        "ID": "reaction_2"
      },
      {
        "Tag": "family",
        "Response": "like",
        "Whitelist": [],
        "SpecialResponses": {
          "BeforeMovie": {
            "ResponsePoint": null,
            "Script": "",
            "Text": "おぉ、「{0}」！これは健康的で楽しいですね！"
          },
          "DuringMovie": {
            "ResponsePoint": null,
            "Script": "/message \"（ペニーは笑っています）」",
            "Text": ""
          },
          "AfterMovie": {
            "ResponsePoint": null,
            "Script": "",
            "Text": "いつかこれを見るために子供たちをしっかり連れて行く必要があるね！"
          }
        },
        "ID": "reaction_3"
      },
      {
        "Tag": "comedy",
        "Response": "like",
        "Whitelist": [],
        "SpecialResponses": {
          "BeforeMovie": {
            "ResponsePoint": null,
            "Script": "",
            "Text": "興奮してる、大笑いしたい気分！"
          },
          "DuringMovie": {
            "ResponsePoint": null,
            "Script": "",
            "Text": "彼らだけ...？ハハハハ！"
          },
          "AfterMovie": {
            "ResponsePoint": null,
            "Script": "",
            "Text": "うわー、笑ってたら全身がけいれんしてきた...！"
          }
        },
        "ID": "reaction_4"
      },
      {
        "Tag": "horror",
        "Response": "dislike",
        "Whitelist": [],
        "SpecialResponses": {
          "BeforeMovie": {
            "ResponsePoint": null,
            "Script": "",
            "Text": "少し緊張してる...ほとんど怖い映画を見ないよ。$s"
          },
          "DuringMovie": {
            "ResponsePoint": null,
            "Script": "/shake Penny 3000/pause 500/emote Penny 28",
            "Text": "見えない...$s"
          },
          "AfterMovie": {
            "ResponsePoint": null,
            "Script": "",
            "Text": "今夜は悪夢を見ないことを願うよ！$s"
          }
        },
        "ID": "reaction_5"
      },
      {
        "Tag": "love",
        "Response": "like",
        "Whitelist": [],
        "SpecialResponses": {
          "BeforeMovie": {
            "ResponsePoint": null,
            "Script": "",
            "Text": "おーぉ、これ見て死にかけてる！"
          },
          "DuringMovie": null,
          "AfterMovie": {
            "ResponsePoint": null,
            "Script": "",
            "Text": "すごい！彼らが別のものを作ることを願ってるわ！"
          }
        },
        "ID": "reaction_6"
      },
      {
        "Tag": "like",
        "Response": "like",
        "Whitelist": [],
        "SpecialResponses": {
          "BeforeMovie": {
            "ResponsePoint": null,
            "Script": "",
            "Text": "ハイ、これに関していくつかの良いことを聞いたことがあるよ！"
          },
          "DuringMovie": null,
          "AfterMovie": {
            "ResponsePoint": null,
            "Script": "",
            "Text": "すごく良かったよ！一緒にこれを見てくれてありがとう！"
          }
        },
        "ID": "reaction_7"
      },
      {
        "Tag": "dislike",
        "Response": "like",
        "Whitelist": [],
        "SpecialResponses": {
          "BeforeMovie": {
            "ResponsePoint": null,
            "Script": "",
            "Text": "これを自分で選択したと言えないけど、心を開いておくようにするよ..."
          },
          "DuringMovie": {
            "ResponsePoint": null,
            "Script": "",
            "Text": "..."
          },
          "AfterMovie": {
            "ResponsePoint": null,
            "Script": "",
            "Text": "あなたのために映画を台無しにしてしまってごめんなさい、ただ本当に私のお気に入りではなかったの..."
          }
        },
        "ID": "reaction_8"
      },
      {
        "Tag": "seen_love",
        "Response": "like",
        "Whitelist": [],
        "SpecialResponses": {
          "BeforeMovie": {
            "ResponsePoint": null,
            "Script": "",
            "Text": "おお、「{0}」！これを{2}で見た！"
          },
          "DuringMovie": null,
          "AfterMovie": null
        },
        "ID": "reaction_9"
      },
      {
        "Tag": "seen_like",
        "Response": "like",
        "Whitelist": [],
        "SpecialResponses": {
          "BeforeMovie": {
            "ResponsePoint": null,
            "Script": "",
            "Text": "{2}とこれを見たわ。とても良かった！"
          },
          "DuringMovie": null,
          "AfterMovie": null
        },
        "ID": "reaction_10"
      },
      {
        "Tag": "seen_dislike",
        "Response": "like",
        "Whitelist": [],
        "SpecialResponses": {
          "BeforeMovie": {
            "ResponsePoint": null,
            "Script": "",
            "Text": "うーん、{2}がこれを見に連れて行ってくれたと思う..."
          },
          "DuringMovie": null,
          "AfterMovie": null
        },
        "ID": "reaction_11"
      }
    ]
  },
  {
    "NPCName": "Pam",
    "Reactions": [
      {
        "Tag": "*",
        "Response": "like",
        "Whitelist": [],
        "SpecialResponses": {
          "BeforeMovie": {
            "ResponsePoint": null,
            "Script": "",
            "Text": "こんにちは、ボウヤ。招待してくれてありがとう。"
          },
          "DuringMovie": null,
          "AfterMovie": {
            "ResponsePoint": null,
            "Script": "",
            "Text": "うん、それほど悪くなかったよ！"
          }
        },
        "ID": "reaction_0"
      }
    ]
  },
  {
    "NPCName": "Krobus",
    "Reactions": [
      {
        "Tag": "fall_movie_0",
        "Response": "like",
        "Whitelist": [],
        "SpecialResponses": {
          "BeforeMovie": {
            "ResponsePoint": null,
            "Script": "",
            "Text": "ちょっと...こんにちは、クロバスと言います。私が分かりますか？$8#$b#誰かが私たちに近づいてきたら、あなたは話しかけますね、いいですか？$8"
          },
          "DuringMovie": {
            "ResponsePoint": "mysterium_shadow",
            "Script": "/message \"クロバスは煮込んでいます...」",
            "Text": "すべての影の人がそういうわけではないです！$8"
          },
          "AfterMovie": {
            "ResponsePoint": null,
            "Script": "",
            "Text": "服を着ることに慣れてないんです...とても不快です！$8"
          }
        },
        "ID": "reaction_0"
      },
      {
        "Tag": "*",
        "Response": "dislike",
        "Whitelist": [],
        "SpecialResponses": {
          "BeforeMovie": {
            "ResponsePoint": null,
            "Script": "",
            "Text": "（エヘン）...こんにちは！ビジュアルエンターテイメントセンターにいてポップコーンを食べることにすごく興奮します。$8#$b#（ひそひそ）...どうしたの？$8"
          },
          "DuringMovie": null,
          "AfterMovie": {
            "ResponsePoint": null,
            "Script": "",
            "Text": "あなたの種族は数時間の間明滅光を見つめて楽しんでるんですか？すごく興味深い...$8"
          }
        },
        "ID": "reaction_1"
      }
    ]
  },
  {
    "NPCName": "Wizard",
    "Reactions": [
      {
        "Tag": "fall_movie_0",
        "Response": "love",
        "Whitelist": [],
        "SpecialResponses": {
          "BeforeMovie": {
            "ResponsePoint": null,
            "Script": "",
            "Text": "今夜このビルに浸っている良く分からない力を感じます..."
          },
          "DuringMovie": {
            "ResponsePoint": null,
            "Script": "/message \"魔術師の目にはきらめきがある...」",
            "Text": "考えてみると...素人はこれがすべて本物の映像だって分からない！"
          },
          "AfterMovie": {
            "ResponsePoint": null,
            "Script": "",
            "Text": "難しい謎を知っている人に対しては、それは深い意味を持ってました..."
          }
        },
        "ID": "reaction_1"
      },
      {
        "Tag": "*",
        "Response": "dislike",
        "Whitelist": [],
        "SpecialResponses": {
          "BeforeMovie": {
            "ResponsePoint": null,
            "Script": "",
            "Text": "..."
          },
          "DuringMovie": null,
          "AfterMovie": {
            "ResponsePoint": null,
            "Script": "",
            "Text": "（これ）のために私に勉強させないつもりですか？"
          }
        },
        "ID": "reaction_0"
      }
    ]
  },
  {
    "NPCName": "George",
    "Reactions": [
      {
        "Tag": "family",
        "Response": "like",
        "Whitelist": [],
        "SpecialResponses": null,
        "ID": "reaction_0"
      },
      {
        "Tag": "classic",
        "Response": "love",
        "Whitelist": [],
        "SpecialResponses": null,
        "ID": "reaction_1"
      },
      {
        "Tag": "*",
        "Response": "dislike",
        "Whitelist": [],
        "SpecialResponses": null,
        "ID": "reaction_2"
      },
      {
        "Tag": "love",
        "Response": "like",
        "Whitelist": [],
        "SpecialResponses": {
          "BeforeMovie": {
            "ResponsePoint": null,
            "Script": "",
            "Text": "これを新聞は「5つ星」にしたので、私はそれを試してみるつもりです。"
          },
          "DuringMovie": null,
          "AfterMovie": {
            "ResponsePoint": null,
            "Script": "",
            "Text": "ヘへ！それは実際かなり良かった！招待してくれてありがとう。"
          }
        },
        "ID": "reaction_3"
      },
      {
        "Tag": "like",
        "Response": "like",
        "Whitelist": [],
        "SpecialResponses": {
          "BeforeMovie": {
            "ResponsePoint": null,
            "Script": "",
            "Text": "うーん...劇場は昔のようなものではありません...でも写真は十分に良いかもしれません。"
          },
          "DuringMovie": null,
          "AfterMovie": {
            "ResponsePoint": null,
            "Script": "",
            "Text": "ヘ。ほとんどの最近の映画と比較すると、悪くなかったです。$h"
          }
        },
        "ID": "reaction_4"
      },
      {
        "Tag": "dislike",
        "Response": "like",
        "Whitelist": [],
        "SpecialResponses": {
          "BeforeMovie": {
            "ResponsePoint": null,
            "Script": "",
            "Text": "うーん...この間に昼寝します。"
          },
          "DuringMovie": null,
          "AfterMovie": {
            "ResponsePoint": null,
            "Script": "",
            "Text": "恥ずかしい！最近彼らが「映画」のために渡すゴミ... "
          }
        },
        "ID": "reaction_5"
      }
    ]
  },
  {
    "NPCName": "Alex",
    "Reactions": [
      {
        "Tag": "fall_movie_1",
        "Response": "love",
        "Whitelist": [],
        "SpecialResponses": null,
        "ID": "reaction_0"
      },
      {
        "Tag": "documentary",
        "Response": "dislike",
        "Whitelist": [],
        "SpecialResponses": null,
        "ID": "reaction_1"
      },
      {
        "Tag": "summer_movie_1",
        "Response": "love",
        "Whitelist": [],
        "SpecialResponses": {
          "BeforeMovie": {
            "ResponsePoint": null,
            "Script": "",
            "Text": "これはかなり面白くて、それを楽しみにしてます。"
          },
          "DuringMovie": null,
          "AfterMovie": {
            "ResponsePoint": null,
            "Script": "",
            "Text": "ああ！本当にそれが気に入った。でもそんなグルテンパックで生き残れるかどうか私は分からない。"
          }
        },
        "ID": "reaction_2"
      },
      {
        "Tag": "love",
        "Response": "like",
        "Whitelist": [],
        "SpecialResponses": {
          "BeforeMovie": {
            "ResponsePoint": null,
            "Script": "",
            "Text": "しばらくそれを見てみたいと思ってました。.チケットをありがとう、@！"
          },
          "DuringMovie": null,
          "AfterMovie": {
            "ResponsePoint": null,
            "Script": "",
            "Text": "すごく良かったよ！私の足はまだ興奮してます。"
          }
        },
        "ID": "reaction_3"
      },
      {
        "Tag": "like",
        "Response": "like",
        "Whitelist": [],
        "SpecialResponses": {
          "BeforeMovie": {
            "ResponsePoint": null,
            "Script": "",
            "Text": "ヘイ、映画を見るのにとても興奮してるよ！おやつが必要だけど..."
          },
          "DuringMovie": null,
          "AfterMovie": {
            "ResponsePoint": null,
            "Script": "",
            "Text": "こんにちは、それはかなり良かったよ。ここに招待してくれてありがとう、@。"
          }
        },
        "ID": "reaction_4"
      },
      {
        "Tag": "dislike",
        "Response": "like",
        "Whitelist": [],
        "SpecialResponses": {
          "BeforeMovie": {
            "ResponsePoint": null,
            "Script": "",
            "Text": "この映画はちょっとオタク向けだけど、見てみるよ。"
          },
          "DuringMovie": null,
          "AfterMovie": {
            "ResponsePoint": null,
            "Script": "",
            "Text": "退屈だったのか、理解できないくらい賢くないのかは分からない...$s"
          }
        },
        "ID": "reaction_5"
      }
    ]
  },
  {
    "NPCName": "Evelyn",
    "Reactions": [
      {
        "Tag": "classic",
        "Response": "love",
        "Whitelist": [],
        "SpecialResponses": null,
        "ID": "reaction_0"
      },
      {
        "Tag": "horror",
        "Response": "dislike",
        "Whitelist": [],
        "SpecialResponses": null,
        "ID": "reaction_1"
      },
      {
        "Tag": "love",
        "Response": "like",
        "Whitelist": [],
        "SpecialResponses": {
          "BeforeMovie": {
            "ResponsePoint": null,
            "Script": "",
            "Text": "この劇場が町にできる前に、20年間は映画を見たことがなかった！$h"
          },
          "DuringMovie": null,
          "AfterMovie": {
            "ResponsePoint": null,
            "Script": "",
            "Text": "それが大好きだった...今、なんで「{2}」が定番とみなされるのかを知ってます。"
          }
        },
        "ID": "reaction_2"
      },
      {
        "Tag": "like",
        "Response": "like",
        "Whitelist": [],
        "SpecialResponses": {
          "BeforeMovie": {
            "ResponsePoint": null,
            "Script": "",
            "Text": "年を取った女性を映画に招待するのはすごく親切なこと。$h"
          },
          "DuringMovie": null,
          "AfterMovie": {
            "ResponsePoint": null,
            "Script": "",
            "Text": "まだまともな映画を作成していてうれしいよ...楽しかった！"
          }
        },
        "ID": "reaction_3"
      },
      {
        "Tag": "dislike",
        "Response": "like",
        "Whitelist": [],
        "SpecialResponses": {
          "BeforeMovie": {
            "ResponsePoint": null,
            "Script": "",
            "Text": "怖い映画のファンではないけど、心を開いておくようにします。"
          },
          "DuringMovie": {
            "ResponsePoint": null,
            "Script": "/shake Evelyn 3000/pause 500/message \"エブリンは目を隠しています」",
            "Text": "もう終わった？$s"
          },
          "AfterMovie": {
            "ResponsePoint": null,
            "Script": "",
            "Text": "ほぼずっと目を閉じないといけなかった... $s"
          }
        },
        "ID": "reaction_4"
      }
    ]
  },
  {
    "NPCName": "Pierre",
    "Reactions": [
      {
        "Tag": "summer_movie_1",
        "Response": "love",
        "Whitelist": [],
        "SpecialResponses": null,
        "ID": "reaction_0"
      },
      {
        "Tag": "love",
        "Response": "like",
        "Whitelist": [],
        "SpecialResponses": {
          "BeforeMovie": {
            "ResponsePoint": null,
            "Script": "",
            "Text": "昔のSF映画を見て育ったので、このジャンルの現代的な見方に興味があります。"
          },
          "DuringMovie": null,
          "AfterMovie": {
            "ResponsePoint": null,
            "Script": "",
            "Text": "ああ！私が期待したものじゃなかった、でも本当にそれが好きになった！本当にウンバスだと識別してます。$h"
          }
        },
        "ID": "reaction_1"
      },
      {
        "Tag": "like",
        "Response": "like",
        "Whitelist": [],
        "SpecialResponses": {
          "BeforeMovie": {
            "ResponsePoint": null,
            "Script": "",
            "Text": "いつも仕事をしてるから、こんなことをするのは本当にうれしい。"
          },
          "DuringMovie": null,
          "AfterMovie": {
            "ResponsePoint": null,
            "Script": "",
            "Text": "悪くない！在庫がある商品はあるかな..."
          }
        },
        "ID": "reaction_2"
      }
    ]
  },
  {
    "NPCName": "Abigail",
    "Reactions": [
      {
        "Tag": "horror",
        "Response": "love",
        "Whitelist": [],
        "SpecialResponses": null,
        "ID": "reaction_0"
      },
      {
        "Tag": "classic",
        "Response": "dislike",
        "Whitelist": [],
        "SpecialResponses": null,
        "ID": "reaction_1"
      },
      {
        "Tag": "summer_movie_0",
        "Response": "like",
        "Whitelist": [],
        "SpecialResponses": {
          "BeforeMovie": {
            "ResponsePoint": null,
            "Script": "",
            "Text": "彼らがプレーリーキングの映画を作ったdaなんて考えられない...それは良いね！"
          },
          "DuringMovie": {
            "ResponsePoint": null,
            "Script": "",
            "Text": "聞いて...それは昔おなじみだった音楽だよ。$h"
          },
          "AfterMovie": {
            "ResponsePoint": null,
            "Script": "",
            "Text": "演技はひどかったけど、まだ素晴らしい時間を過ごせた。$h"
          }
        },
        "ID": "reaction_2"
      },
      {
        "Tag": "spring_movie_1",
        "Response": "like",
        "Whitelist": [],
        "SpecialResponses": {
          "BeforeMovie": {
            "ResponsePoint": null,
            "Script": "",
            "Text": "「この活気溢れた世界を探検する」ことに興奮してる...んだよね？$h"
          },
          "DuringMovie": {
            "ResponsePoint": null,
            "Script": "",
            "Text": "知らなかった！"
          },
          "AfterMovie": {
            "ResponsePoint": null,
            "Script": "",
            "Text": "本当に面白かったよ。一番アライグマが好きだった...彼らはすごくかわいいよ！$h"
          }
        },
        "ID": "reaction_3"
      },
      {
        "Tag": "love",
        "Response": "like",
        "Whitelist": [],
        "SpecialResponses": {
          "BeforeMovie": {
            "ResponsePoint": null,
            "Script": "",
            "Text": "ホラー映画が大好き...怖いのが良いよ！$h"
          },
          "DuringMovie": {
            "ResponsePoint": null,
            "Script": "/shake Abigail 3000/pause 500/message \"アビゲイルが笑ってる！」",
            "Text": "ははっ！怖くなくて大好きだよ。$h"
          },
          "AfterMovie": {
            "ResponsePoint": null,
            "Script": "",
            "Text": "かなりキャンピーだけど、それが好きだったの。$h"
          }
        },
        "ID": "reaction_4"
      },
      {
        "Tag": "like",
        "Response": "like",
        "Whitelist": [],
        "SpecialResponses": {
          "BeforeMovie": {
            "ResponsePoint": null,
            "Script": "",
            "Text": "ヘイ！招待してくれてありがとう、映画を見に行くのが大好きなんだ。$h"
          },
          "DuringMovie": null,
          "AfterMovie": {
            "ResponsePoint": null,
            "Script": "",
            "Text": "おもしろかったわ…同じ状況で私は何をしたかな？"
          }
        },
        "ID": "reaction_5"
      },
      {
        "Tag": "dislike",
        "Response": "like",
        "Whitelist": [],
        "SpecialResponses": {
          "BeforeMovie": {
            "ResponsePoint": null,
            "Script": "",
            "Text": "予告編を見ると、本当のスヌーズフェストのように見えるわ... $6"
          },
          "DuringMovie": {
            "ResponsePoint": null,
            "Script": "",
            "Text": "何か面白いことがあったら起こしてね。$6"
          },
          "AfterMovie": {
            "ResponsePoint": null,
            "Script": "",
            "Text": "（あ～ぁ） ...かなり退屈だ。$6"
          }
        },
        "ID": "reaction_6"
      }
    ]
  },
  {
    "NPCName": "Caroline",
    "Reactions": [
      {
        "Tag": "spring_movie_0",
        "Response": "love",
        "Whitelist": [],
        "SpecialResponses": null,
        "ID": "reaction_0"
      },
      {
        "Tag": "summer_movie_1",
        "Response": "dislike",
        "Whitelist": [],
        "SpecialResponses": null,
        "ID": "reaction_1"
      },
      {
        "Tag": "summer_movie_0",
        "Response": "love",
        "Whitelist": [],
        "SpecialResponses": {
          "BeforeMovie": {
            "ResponsePoint": null,
            "Script": "",
            "Text": "私はいつもワイルド・ウエストの映画が好きだったから、これ見て本当に興奮する！"
          },
          "DuringMovie": null,
          "AfterMovie": {
            "ResponsePoint": null,
            "Script": "",
            "Text": "すごく良かったよ！服装ぜんぶから、本物のように感じたわ。"
          }
        },
        "ID": "reaction_2"
      },
      {
        "Tag": "love",
        "Response": "like",
        "Whitelist": [],
        "SpecialResponses": {
          "BeforeMovie": {
            "ResponsePoint": null,
            "Script": "",
            "Text": "この映画はとてもかわいい、誰かが招待してることを心から望んでたわ！"
          },
          "DuringMovie": {
            "ResponsePoint": null,
            "Script": "",
            "Text": "貧しい人が大丈夫であることを願ってるの... $s"
          },
          "AfterMovie": {
            "ResponsePoint": null,
            "Script": "",
            "Text": "それは可愛かったわ。私を招待してくれてありがとう！"
          }
        },
        "ID": "reaction_3"
      },
      {
        "Tag": "like",
        "Response": "like",
        "Whitelist": [],
        "SpecialResponses": {
          "BeforeMovie": {
            "ResponsePoint": null,
            "Script": "",
            "Text": "'{0}'...これが何なのか分からない！暴力っぽくないことを願ってる。"
          },
          "DuringMovie": null,
          "AfterMovie": {
            "ResponsePoint": null,
            "Script": "",
            "Text": "悪くなかったよ！家にいるときはアビゲイルにそれを質問しなければいけないでしょう、彼女は見たことがあると思う。$h"
          }
        },
        "ID": "reaction_4"
      },
      {
        "Tag": "dislike",
        "Response": "like",
        "Whitelist": [],
        "SpecialResponses": {
          "BeforeMovie": {
            "ResponsePoint": null,
            "Script": "",
            "Text": "これが失望に繋がるだろうと感じてる...でもまだ試してみることに興味がある。"
          },
          "DuringMovie": null,
          "AfterMovie": {
            "ResponsePoint": null,
            "Script": "",
            "Text": "ばかみたいだった...ピエールがそれを望んでいるに違いない。$s"
          }
        },
        "ID": "reaction_5"
      }
    ]
  },
  {
    "NPCName": "Harvey",
    "Reactions": [
      {
        "Tag": "spring_movie_1",
        "Response": "like",
        "Whitelist": [],
        "SpecialResponses": {
          "BeforeMovie": {
            "ResponsePoint": null,
            "Script": "",
            "Text": "これについては緊張するね...（ゴクリ）"
          },
          "DuringMovie": {
            "ResponsePoint": null,
            "Script": "/shake Harvey 3000/pause 500/message \"ハーヴィーは揺れてる！」",
            "Text": "怖いな！$8"
          },
          "AfterMovie": {
            "ResponsePoint": null,
            "Script": "",
            "Text": "私は高所恐怖症なので、この高騰してる空中ショットは本当に私のところに来ました...でも全体的に楽しい時間を過ごせたよ。$h"
          }
        },
        "ID": "reaction_3"
      },
      {
        "Tag": "classic",
        "Response": "love",
        "Whitelist": [],
        "SpecialResponses": null,
        "ID": "reaction_0"
      },
      {
        "Tag": "action",
        "Response": "dislike",
        "Whitelist": [],
        "SpecialResponses": null,
        "ID": "reaction_1"
      },
      {
        "Tag": "horror",
        "Response": "dislike",
        "Whitelist": [],
        "SpecialResponses": null,
        "ID": "reaction_2"
      },
      {
        "Tag": "love",
        "Response": "like",
        "Whitelist": [],
        "SpecialResponses": {
          "BeforeMovie": {
            "ResponsePoint": null,
            "Script": "",
            "Text": "ズズシティタイムズでこの映画を高評価しているレビューを読んだんだ..."
          },
          "DuringMovie": {
            "ResponsePoint": null,
            "Script": "",
            "Text": "それは本当に考えさせるね？"
          },
          "AfterMovie": {
            "ResponsePoint": null,
            "Script": "",
            "Text": "目立ってたよ！私を連れ出してくれて本当にうれしいよ@。$h"
          }
        },
        "ID": "reaction_4"
      },
      {
        "Tag": "like",
        "Response": "like",
        "Whitelist": [],
        "SpecialResponses": {
          "BeforeMovie": {
            "ResponsePoint": null,
            "Script": "",
            "Text": "あんまり映画を見ないけど、これは好評だったよね？"
          },
          "DuringMovie": null,
          "AfterMovie": {
            "ResponsePoint": null,
            "Script": "",
            "Text": "おもしろかったよ！少し{0}について考えてみる。"
          }
        },
        "ID": "reaction_5"
      },
      {
        "Tag": "dislike",
        "Response": "like",
        "Whitelist": [],
        "SpecialResponses": {
          "BeforeMovie": {
            "ResponsePoint": null,
            "Script": "",
            "Text": "この映画は私にとってはちょっと激しいかな...$s"
          },
          "DuringMovie": {
            "ResponsePoint": null,
            "Script": "/shake Harvey 3000/pause 500/message \"ハーヴィーの血圧は急上昇している！」",
            "Text": "かすかに感じる...$8"
          },
          "AfterMovie": {
            "ResponsePoint": null,
            "Script": "",
            "Text": "その映画の後に体が炎症を起こしていると感じるよ...$s"
          }
        },
        "ID": "reaction_6"
      }
    ]
  },
  {
    "NPCName": "Gus",
    "Reactions": [
      {
        "Tag": "summer_movie_1",
        "Response": "love",
        "Whitelist": [],
        "SpecialResponses": {
          "BeforeMovie": {
            "ResponsePoint": null,
            "Script": "",
            "Text": "テレビでこれのコマーシャルを見たんだ。本当に面白そうだね！"
          },
          "DuringMovie": null,
          "AfterMovie": {
            "ResponsePoint": null,
            "Script": "",
            "Text": "アマチュア愛好家として、グルテンベースの食べ物への奇妙なこだわりが愉快だったよ。$h"
          }
        },
        "ID": "reaction_0"
      },
      {
        "Tag": "winter_movie_0",
        "Response": "love",
        "Whitelist": [],
        "SpecialResponses": {
          "BeforeMovie": {
            "ResponsePoint": null,
            "Script": "",
            "Text": "「{0}」を確認するまでは休日のようには感じないな！"
          },
          "DuringMovie": null,
          "AfterMovie": {
            "ResponsePoint": null,
            "Script": "",
            "Text": "それは心温まるものだった...そしてどういうわけか、彼らはその伝説的な果物をかなり美味しそうに見せてるんだ。いつか食べて味わってみたいよ。"
          }
        },
        "ID": "reaction_1"
      },
      {
        "Tag": "fall_movie_0",
        "Response": "dislike",
        "Whitelist": [],
        "SpecialResponses": {
          "BeforeMovie": {
            "ResponsePoint": null,
            "Script": "",
            "Text": "この映画は「型にはまらない」って彼らは言ってる...それは悪い意味なのかな？$s"
          },
          "DuringMovie": null,
          "AfterMovie": {
            "ResponsePoint": null,
            "Script": "",
            "Text": "そのポイントの1つは何？分からない。多分私は年を取りすぎてるんだ。$s"
          }
        },
        "ID": "reaction_3"
      },
      {
        "Tag": "like",
        "Response": "like",
        "Whitelist": [],
        "SpecialResponses": {
          "BeforeMovie": {
            "ResponsePoint": null,
            "Script": "",
            "Text": "（クンクン）（クンクン）...何かおいしそうな香りがするね..."
          },
          "DuringMovie": null,
          "AfterMovie": {
            "ResponsePoint": null,
            "Script": "",
            "Text": "悪くない、全然。来てくれて本当にうれしい！"
          }
        },
        "ID": "reaction_2"
      }
    ]
  },
  {
    "NPCName": "Lewis",
    "Reactions": [
      {
        "Tag": "summer_movie_0",
        "Response": "like",
        "Whitelist": [],
        "SpecialResponses": {
          "BeforeMovie": {
            "ResponsePoint": null,
            "Script": "",
            "Text": "子供の頃に、カウボーイの映画を見たんだ...アートがまだ存在しているのを見れてうれしいよ。"
          },
          "DuringMovie": {
            "ResponsePoint": "PK_villain",
            "Script": "/メッセージ「ルイス町長深く考え事をしてるようです…」",
            "Text": "（彼がどんな種類のヒゲワックスを使っているのか気になる？）"
          },
          "AfterMovie": {
            "ResponsePoint": null,
            "Script": "",
            "Text": "へー、それは素晴らしかったね！本当に私を連れ戻したね...$h"
          }
        },
        "ID": "reaction_3"
      },
      {
        "Tag": "spring_movie_1",
        "Response": "love",
        "Whitelist": [],
        "SpecialResponses": {
          "BeforeMovie": {
            "ResponsePoint": null,
            "Script": "",
            "Text": "町長自身がこの映画を私におススメしたんだ！"
          },
          "DuringMovie": null,
          "AfterMovie": {
            "ResponsePoint": null,
            "Script": "",
            "Text": "すごい！彼らはスターデューバレーをとても美しく見せたよね？彼らがペリカンタウン自体を特集していたら... $h"
          }
        },
        "ID": "reaction_4"
      },
      {
        "Tag": "family",
        "Response": "like",
        "Whitelist": [],
        "SpecialResponses": null,
        "ID": "reaction_0"
      },
      {
        "Tag": "classic",
        "Response": "like",
        "Whitelist": [],
        "SpecialResponses": null,
        "ID": "reaction_1"
      },
      {
        "Tag": "*",
        "Response": "dislike",
        "Whitelist": [],
        "SpecialResponses": null,
        "ID": "reaction_2"
      },
      {
        "Tag": "like",
        "Response": "like",
        "Whitelist": [],
        "SpecialResponses": {
          "BeforeMovie": {
            "ResponsePoint": null,
            "Script": "",
            "Text": "町長として、ここのコミュニティでどんな映画が上映されてるか、知る必要があるんだよ。私たちは心配するべき次世代の優しい心を持ってるよ！"
          },
          "DuringMovie": null,
          "AfterMovie": {
            "ResponsePoint": null,
            "Script": "",
            "Text": "ああ！それはまったく悪くなかった...私はこれを「町長承認」といってるよ。$h"
          }
        },
        "ID": "reaction_5"
      },
      {
        "Tag": "dislike",
        "Response": "like",
        "Whitelist": [],
        "SpecialResponses": {
          "BeforeMovie": {
            "ResponsePoint": null,
            "Script": "",
            "Text": "うーん...最近の若者たちが何を見てるのか、それを見るのはおもしろいだろうなぁ..."
          },
          "DuringMovie": null,
          "AfterMovie": {
            "ResponsePoint": null,
            "Script": "",
            "Text": "ええと...この映画の中に含まれるメッセージはこの地域社会に役立つものだろうか？"
          }
        },
        "ID": "reaction_6"
      }
    ]
  },
  {
    "NPCName": "Jodi",
    "Reactions": [
      {
        "Tag": "winter_movie_1",
        "Response": "love",
        "Whitelist": [],
        "SpecialResponses": null,
        "ID": "reaction_0"
      },
      {
        "Tag": "love",
        "Response": "like",
        "Whitelist": [],
        "SpecialResponses": {
          "BeforeMovie": {
            "ResponsePoint": null,
            "Script": "",
            "Text": "昔、この映画を一度見たんだ。すごくロマンチックだったよ！"
          },
          "DuringMovie": null,
          "AfterMovie": {
            "ResponsePoint": null,
            "Script": "",
            "Text": "素敵なものだね...映画のテーマにかなり共鳴したよ。連れてきてくれてありがとう！"
          }
        },
        "ID": "reaction_1"
      },
      {
        "Tag": "like",
        "Response": "like",
        "Whitelist": [],
        "SpecialResponses": {
          "BeforeMovie": {
            "ResponsePoint": null,
            "Script": "",
            "Text": "席が豪華だと願ってるよ、私は一日中そこにいました！"
          },
          "DuringMovie": null,
          "AfterMovie": {
            "ResponsePoint": null,
            "Script": "",
            "Text": "映画は好きじゃないけど...楽しい時間を過ごしたよ！ありがとう、@。"
          }
        },
        "ID": "reaction_2"
      }
    ]
  },
  {
    "NPCName": "Sam",
    "Reactions": [
      {
        "Tag": "summer_movie_1",
        "Response": "love",
        "Whitelist": [],
        "SpecialResponses": {
          "BeforeMovie": {
            "ResponsePoint": null,
            "Script": "",
            "Text": "おお、これにとても興奮している！その中で素晴らしいサウンドトラックが流れていると聞いたよ。"
          },
          "DuringMovie": {
            "ResponsePoint": null,
            "Script": "/playSound reward/emote Sam 32/message Sam \"サムは彼の笑いをこらえられない！」",
            "Text": "この映画はおもしろい！どうやって彼らはこんな内容を思いついたのかな？$h"
          },
          "AfterMovie": {
            "ResponsePoint": null,
            "Script": "",
            "Text": "「ちょっと」...誰にも言わないで、でも私はウンバスと同じ種類の靴下を履いてます。"
          }
        },
        "ID": "reaction_1"
      },
      {
        "Tag": "classic",
        "Response": "dislike",
        "Whitelist": [],
        "SpecialResponses": null,
        "ID": "reaction_0"
      },
      {
        "Tag": "horror",
        "Response": "like",
        "Whitelist": [],
        "SpecialResponses": {
          "BeforeMovie": {
            "ResponsePoint": null,
            "Script": "",
            "Text": "だから、怖い映画が好きなんですね、ふふ？ちょっとびっくり！"
          },
          "DuringMovie": null,
          "AfterMovie": {
            "ResponsePoint": null,
            "Script": "",
            "Text": "かなり良かったよ！ほとんど映画は怖くないけど、でもたまに怖いのもあるね...これを見るためにヴィンセントを連れて行くつもりはないよ。"
          }
        },
        "ID": "reaction_2"
      },
      {
        "Tag": "like",
        "Response": "like",
        "Whitelist": [],
        "SpecialResponses": {
          "BeforeMovie": {
            "ResponsePoint": null,
            "Script": "",
            "Text": "ハイ、私を招待してくれてありがとう、@...私たちの町にいま、映画館があることは本当に素晴らしいことだね。"
          },
          "DuringMovie": null,
          "AfterMovie": {
            "ResponsePoint": null,
            "Script": "",
            "Text": "悪くなかったよ！これを見るためにヴィンセントを連れて行く必要があるかも。"
          }
        },
        "ID": "reaction_3"
      },
      {
        "Tag": "dislike",
        "Response": "like",
        "Whitelist": [],
        "SpecialResponses": {
          "BeforeMovie": {
            "ResponsePoint": null,
            "Script": "",
            "Text": "話がたくさんある古い映画だよね？うーん... $s"
          },
          "DuringMovie": {
            "ResponsePoint": null,
            "Script": "/message Sam \"サムは彼のハンドヘルドビデオゲームシステムをプレイしています。」",
            "Text": "ええと？おぉ！えぇ...その映画は…おもしろい…$10"
          },
          "AfterMovie": {
            "ResponsePoint": null,
            "Script": "",
            "Text": "えぇ...んー…1人のキャラクターが面白かった...そして、ええと...ええと...$10"
          }
        },
        "ID": "reaction_4"
      }
    ]
  },
  {
    "NPCName": "Vincent",
    "Reactions": [
      {
        "Tag": "horror",
        "Response": "dislike",
        "Whitelist": [],
        "SpecialResponses": null,
        "ID": "reaction_0"
      },
      {
        "Tag": "documentary",
        "Response": "dislike",
        "Whitelist": [],
        "SpecialResponses": null,
        "ID": "reaction_1"
      },
      {
        "Tag": "classic",
        "Response": "dislike",
        "Whitelist": [],
        "SpecialResponses": null,
        "ID": "reaction_2"
      },
      {
        "Tag": "*",
        "Response": "love",
        "Whitelist": [],
        "SpecialResponses": null,
        "ID": "reaction_3"
      },
      {
        "Tag": "love",
        "Response": "like",
        "Whitelist": [],
        "SpecialResponses": {
          "BeforeMovie": {
            "ResponsePoint": null,
            "Script": "",
            "Text": "とても興奮してるよ！お母さんもお菓子を食べられるって言ってる！$h"
          },
          "DuringMovie": {
            "ResponsePoint": null,
            "Script": "/jump Vincent/pause 400/playSound reward/message \"ヴィンセントは衝撃を受けてる！」",
            "Text": ""
          },
          "AfterMovie": {
            "ResponsePoint": null,
            "Script": "",
            "Text": "とても楽しかったよ！また会いたいね！$h"
          }
        },
        "ID": "reaction_4"
      },
      {
        "Tag": "dislike",
        "Response": "like",
        "Whitelist": [],
        "SpecialResponses": {
          "BeforeMovie": {
            "ResponsePoint": null,
            "Script": "",
            "Text": "で...でもね...この映画は大人向けですよね？$s"
          },
          "DuringMovie": {
            "ResponsePoint": null,
            "Script": "/shake Vincent 250/pause 500/shake Vincent 250/pause 500/emote Vincent 28/message \"ヴィンセントは彼の席にそわそわしてる。」",
            "Text": ""
          },
          "AfterMovie": {
            "ResponsePoint": null,
            "Script": "",
            "Text": "退屈だった...何も分からなかった。$s"
          }
        },
        "ID": "reaction_5"
      }
    ]
  },
  {
    "NPCName": "Kent",
    "Reactions": [
      {
        "Tag": "horror",
        "Response": "dislike",
        "Whitelist": [],
        "SpecialResponses": null,
        "ID": "reaction_0"
      },
      {
        "Tag": "like",
        "Response": "like",
        "Whitelist": [],
        "SpecialResponses": {
          "BeforeMovie": {
            "ResponsePoint": null,
            "Script": "",
            "Text": "映画に招待してくれてありがとう@。一般のライフスタイルに戻って調整するのは簡単ではないけど、私を本当に歓迎するのをあなたは手伝ってくれました。"
          },
          "DuringMovie": {
            "ResponsePoint": null,
            "Script": "/emote Kent 32/message \"ケントは稀な笑顔を見せています。」",
            "Text": "これは素晴らしいな...それはもっと単純だった時代を思い出させる...$h"
          },
          "AfterMovie": {
            "ResponsePoint": null,
            "Script": "",
            "Text": "それは楽しかったよ。君が映画に夢中になると、不安や心配はすべて消えるよ。"
          }
        },
        "ID": "reaction_1"
      },
      {
        "Tag": "dislike",
        "Response": "like",
        "Whitelist": [],
        "SpecialResponses": {
          "BeforeMovie": {
            "ResponsePoint": null,
            "Script": "",
            "Text": "この映画についてよく分からない..."
          },
          "DuringMovie": {
            "ResponsePoint": null,
            "Script": "/emote Kent 28/message \"ケントは冷や汗をかいています...」",
            "Text": ""
          },
          "AfterMovie": {
            "ResponsePoint": null,
            "Script": "",
            "Text": "それはオレにとって困難だった。それでも、オレを招待してくれてありがとう。"
          }
        },
        "ID": "reaction_2"
      }
    ]
  },
  {
    "NPCName": "Clint",
    "Reactions": [
      {
        "Tag": "winter_movie_1",
        "Response": "dislike",
        "Whitelist": [],
        "SpecialResponses": {
          "BeforeMovie": {
            "ResponsePoint": null,
            "Script": "",
            "Text": "この映画はロマンスだよな？（はぁ～）$s"
          },
          "DuringMovie": {
            "ResponsePoint": "guyEnters",
            "Script": "/emote Clint 12/message \"クリントは睨み付けています」",
            "Text": "なんで彼女はその男が好きなんだろうか？君がオレに尋ねるのは、全くもって非現実的だ... $3"
          },
          "AfterMovie": {
            "ResponsePoint": null,
            "Script": "",
            "Text": "あの映画は憂鬱だった... $s"
          }
        },
        "ID": "reaction_1"
      },
      {
        "Tag": "like",
        "Response": "like",
        "Whitelist": [],
        "SpecialResponses": {
          "BeforeMovie": {
            "ResponsePoint": null,
            "Script": "",
            "Text": "オレはそれが「みんなの夜」だと思うんだ、ハァッ？それはオレ自身のスナックを買わなきゃいけないことを意味してるのか？^おー...そ ...それなら、これはデートかい？$4"
          },
          "DuringMovie": {
            "ResponsePoint": null,
            "Script": "/message \"クリントはマークのついていないフラスコから一服しています。」",
            "Text": "それはただの...（ヒック）...Jojaコーラさ。$h^（ヒソヒソ） ...あんたが...うん…疲れたなら…あんたはオレの...オレの肩に頭を置くことができる。ヘへ...そうじゃない！$4"
          },
          "AfterMovie": {
            "ResponsePoint": null,
            "Script": "",
            "Text": "おい...それはおもしろかった...よな？$h"
          }
        },
        "ID": "reaction_0"
      }
    ]
  },
  {
    "NPCName": "Emily",
    "Reactions": [
      {
        "Tag": "winter_movie_0",
        "Response": "love",
        "Whitelist": [],
        "SpecialResponses": null,
        "ID": "reaction_0"
      },
      {
        "Tag": "horror",
        "Response": "dislike",
        "Whitelist": [],
        "SpecialResponses": null,
        "ID": "reaction_1"
      },
      {
        "Tag": "spring_movie_1",
        "Response": "like",
        "Whitelist": [],
        "SpecialResponses": {
          "BeforeMovie": {
            "ResponsePoint": null,
            "Script": "",
            "Text": "この映画の準備のために一握りのナッツを食べた...頭に良い食べ物！"
          },
          "DuringMovie": null,
          "AfterMovie": {
            "ResponsePoint": null,
            "Script": "",
            "Text": "オレは昔より少し賢くなったと思うが...そうだよな？"
          }
        },
        "ID": "reaction_3"
      },
      {
        "Tag": "love",
        "Response": "like",
        "Whitelist": [],
        "SpecialResponses": {
          "BeforeMovie": {
            "ResponsePoint": null,
            "Script": "",
            "Text": "この映画のポスターを見たとき、頭の中にすごくポジティブな感覚を感じたんだ。$h"
          },
          "DuringMovie": null,
          "AfterMovie": {
            "ResponsePoint": null,
            "Script": "",
            "Text": "あの映画はある意味とてもスピリチュアルだった...同意しないか？オレはそれが大好きだったよ！$h"
          }
        },
        "ID": "reaction_2"
      },
      {
        "Tag": "like",
        "Response": "like",
        "Whitelist": [],
        "SpecialResponses": {
          "BeforeMovie": {
            "ResponsePoint": null,
            "Script": "",
            "Text": "君と一緒に映画が見れてうれしいよ！スクリーンの中で完全に迷子になる傾向があるんだ。"
          },
          "DuringMovie": null,
          "AfterMovie": {
            "ResponsePoint": null,
            "Script": "",
            "Text": "それ以来ポジティブに感じるよ...それがいい映画だったってことだな！$h"
          }
        },
        "ID": "reaction_4"
      },
      {
        "Tag": "dislike",
        "Response": "like",
        "Whitelist": [],
        "SpecialResponses": {
          "BeforeMovie": {
            "ResponsePoint": null,
            "Script": "",
            "Text": "ふつうはもっとポジティブな映画を見に行くから、これは面白いだろう。"
          },
          "DuringMovie": {
            "ResponsePoint": null,
            "Script": "/message \"エミリーは自分にささやいています...」",
            "Text": "ヨーバ、この映画の暗いエネルギーから私を守って。$7"
          },
          "AfterMovie": {
            "ResponsePoint": null,
            "Script": "",
            "Text": "私のエネルギーレベルはそれから低いの... $3"
          }
        },
        "ID": "reaction_5"
      }
    ]
  },
  {
    "NPCName": "Haley",
    "Reactions": [
      {
        "Tag": "winter_movie_1",
        "Response": "like",
        "Whitelist": [],
        "SpecialResponses": {
          "BeforeMovie": {
            "ResponsePoint": null,
            "Script": "",
            "Text": "むーん...ここは暖かくて良いわね。冬は映画を見に行くことが私のお気に入りの時期なの。$h"
          },
          "DuringMovie": null,
          "AfterMovie": {
            "ResponsePoint": null,
            "Script": "",
            "Text": "とてもロマンチックだった。"
          }
        },
        "ID": "reaction_3"
      },
      {
        "Tag": "winter_movie_0",
        "Response": "like",
        "Whitelist": [],
        "SpecialResponses": {
          "BeforeMovie": {
            "ResponsePoint": null,
            "Script": "",
            "Text": "むむむ...ここは暖かくて良いわね。冬は映画を見に行くことが私のお気に入りの時期なの。$h"
          },
          "DuringMovie": null,
          "AfterMovie": {
            "ResponsePoint": null,
            "Script": "",
            "Text": "良い結末だったことがうれしい！"
          }
        },
        "ID": "reaction_4"
      },
      {
        "Tag": "classic",
        "Response": "love",
        "Whitelist": [],
        "SpecialResponses": null,
        "ID": "reaction_0"
      },
      {
        "Tag": "summer_movie_1",
        "Response": "dislike",
        "Whitelist": [],
        "SpecialResponses": null,
        "ID": "reaction_1"
      },
      {
        "Tag": "summer_movie_0",
        "Response": "dislike",
        "Whitelist": [],
        "SpecialResponses": null,
        "ID": "reaction_2"
      },
      {
        "Tag": "dislike",
        "Response": "like",
        "Whitelist": [],
        "SpecialResponses": {
          "BeforeMovie": {
            "ResponsePoint": null,
            "Script": "",
            "Text": "ああ、これは「ファンタジー」映画の1つね？$7"
          },
          "DuringMovie": null,
          "AfterMovie": {
            "ResponsePoint": null,
            "Script": "",
            "Text": "（は～ぁ）...何？ああ…その映画はまた何についてなの？$7"
          }
        },
        "ID": "reaction_5"
      },
      {
        "Tag": "like",
        "Response": "like",
        "Whitelist": [],
        "SpecialResponses": {
          "BeforeMovie": {
            "ResponsePoint": null,
            "Script": "",
            "Text": "みんなこの映画について話しているから、私はそれを見たいの。"
          },
          "DuringMovie": null,
          "AfterMovie": {
            "ResponsePoint": null,
            "Script": "",
            "Text": "その最後のシーン...どういう意味？"
          }
        },
        "ID": "reaction_6"
      }
    ]
  },
  {
    "NPCName": "Maru",
    "Reactions": [
      {
        "Tag": "spring_movie_1",
        "Response": "love",
        "Whitelist": [],
        "SpecialResponses": {
          "BeforeMovie": {
            "ResponsePoint": null,
            "Script": "",
            "Text": "こんにちは、@！私はこれを楽しみにしてるの...たくさん学べることを願ってる！$h"
          },
          "DuringMovie": {
            "ResponsePoint": null,
            "Script": "/emote Maru 32/playSound reward/message \"マルがメモを取っています！」",
            "Text": "ああ、分かったわ...とてもおもしろい！"
          },
          "AfterMovie": {
            "ResponsePoint": null,
            "Script": "",
            "Text": "本当に面白かったね！大きな都市でこんなにたくさんの命が見つかるとは思えなかった。"
          }
        },
        "ID": "reaction_2"
      },
      {
        "Tag": "summer_movie_1",
        "Response": "love",
        "Whitelist": [],
        "SpecialResponses": {
          "BeforeMovie": {
            "ResponsePoint": null,
            "Script": "",
            "Text": "それはSF映画よね？SFで好きなことの1つは、思い付くすべてのおかしな技術を見ていること。"
          },
          "DuringMovie": null,
          "AfterMovie": {
            "ResponsePoint": null,
            "Script": "",
            "Text": "まあ、私は望遠鏡を通して（あれ）のようなものを見たことがないよ...でも本当に素晴らしかった！$h"
          }
        },
        "ID": "reaction_3"
      },
      {
        "Tag": "like",
        "Response": "like",
        "Whitelist": [],
        "SpecialResponses": {
          "BeforeMovie": {
            "ResponsePoint": null,
            "Script": "",
            "Text": "映画が悪くても、劇場に行くのが本当に好き！$h"
          },
          "DuringMovie": null,
          "AfterMovie": {
            "ResponsePoint": null,
            "Script": "",
            "Text": "最後のシーンは、面白い選択だったね。彼らがそれで何を意味してたと思う？"
          }
        },
        "ID": "reaction_4"
      }
    ]
  },
  {
    "NPCName": "Sebastian",
    "Reactions": [
      {
        "Tag": "horror",
        "Response": "love",
        "Whitelist": [],
        "SpecialResponses": null,
        "ID": "reaction_0"
      },
      {
        "Tag": "classic",
        "Response": "dislike",
        "Whitelist": [],
        "SpecialResponses": null,
        "ID": "reaction_1"
      },
      {
        "Tag": "spring_movie_0",
        "Response": "dislike",
        "Whitelist": [],
        "SpecialResponses": null,
        "ID": "reaction_2"
      },
      {
        "Tag": "love",
        "Response": "like",
        "Whitelist": [],
        "SpecialResponses": {
          "BeforeMovie": {
            "ResponsePoint": null,
            "Script": "",
            "Text": "こんにちは。この映画はかなり厳しいって聞いたわ...楽しみにしてる。$h"
          },
          "DuringMovie": {
            "ResponsePoint": null,
            "Script": "/emote Sebastian 32/message \"セバスチャンはニヤリとしています。」",
            "Text": "この映画の撮影は次のレベルだな。"
          },
          "AfterMovie": {
            "ResponsePoint": null,
            "Script": "",
            "Text": "オレがしばらくの間見た中では最高傑作だ...どうやってこの特殊効果のいくつかを実践したんだろうか？$h"
          }
        },
        "ID": "reaction_3"
      },
      {
        "Tag": "like",
        "Response": "like",
        "Whitelist": [],
        "SpecialResponses": {
          "BeforeMovie": {
            "ResponsePoint": null,
            "Script": "",
            "Text": "（肩をすくめる）...映画のポスターがかなりかっこいいから、中に入ったよ。"
          },
          "DuringMovie": null,
          "AfterMovie": {
            "ResponsePoint": null,
            "Script": "",
            "Text": "これまでで一番じゃなかったが、かなり良い時間を過ごしたよ...招待してくれてありがとう。"
          }
        },
        "ID": "reaction_4"
      },
      {
        "Tag": "dislike",
        "Response": "like",
        "Whitelist": [],
        "SpecialResponses": {
          "BeforeMovie": {
            "ResponsePoint": null,
            "Script": "",
            "Text": "それが短いことを願ってる..."
          },
          "DuringMovie": null,
          "AfterMovie": {
            "ResponsePoint": null,
            "Script": "",
            "Text": "おそらく対象読者にとって素晴らしい映画だが、オレにとってはそうではないな。"
          }
        },
        "ID": "reaction_5"
      }
    ]
  },
  {
    "NPCName": "Robin",
    "Reactions": [
      {
        "Tag": "action",
        "Response": "love",
        "Whitelist": [],
        "SpecialResponses": null,
        "ID": "reaction_0"
      },
      {
        "Tag": "love",
        "Response": "like",
        "Whitelist": [],
        "SpecialResponses": {
          "BeforeMovie": {
            "ResponsePoint": null,
            "Script": "",
            "Text": "最近ちょっと鈍い感じがあったから、アクション満載の映画はまさにいま必要としているものだったよ。"
          },
          "DuringMovie": null,
          "AfterMovie": {
            "ResponsePoint": null,
            "Script": "",
            "Text": "今、すべてだめになった！素晴らしかったな。$h"
          }
        },
        "ID": "reaction_1"
      },
      {
        "Tag": "like",
        "Response": "like",
        "Whitelist": [],
        "SpecialResponses": {
          "BeforeMovie": {
            "ResponsePoint": null,
            "Script": "",
            "Text": "この映画が何についてなのか分からないが、全然気にしないぞ！家から出るのはいいことだ。"
          },
          "DuringMovie": null,
          "AfterMovie": {
            "ResponsePoint": null,
            "Script": "",
            "Text": "とても楽しかったよ@。これができてうれしいよ。"
          }
        },
        "ID": "reaction_2"
      }
    ]
  },
  {
    "NPCName": "Demetrius",
    "Reactions": [
      {
        "Tag": "winter_movie_1",
        "Response": "dislike",
        "Whitelist": [],
        "SpecialResponses": {
          "BeforeMovie": {
            "ResponsePoint": null,
            "Script": "",
            "Text": "雪の中で一瞬でぶつかると、マジで血が流れるぞ。"
          },
          "DuringMovie": {
            "ResponsePoint": "zuzucityexpress_mind_heart",
            "Script": "/message \"ディメトリウスは彼の額にしわを寄せています。」",
            "Text": "心の憧れ...？おぉ！「大脳辺縁系のオキシトシン濃度の上昇」を意味しますね。"
          },
          "AfterMovie": {
            "ResponsePoint": null,
            "Script": "",
            "Text": "その頃から映画の芸術は大きく進歩したよね？"
          }
        },
        "ID": "reaction_0"
      },
      {
        "Tag": "summer_movie_1",
        "Response": "love",
        "Whitelist": [],
        "SpecialResponses": {
          "BeforeMovie": {
            "ResponsePoint": null,
            "Script": "",
            "Text": "この映画はおそらく「未来的な」社会で行われてる...それがどのように見えるのか、それを見るのは面白いだろうね！"
          },
          "DuringMovie": null,
          "AfterMovie": {
            "ResponsePoint": null,
            "Script": "",
            "Text": "素晴らしい映画だよ...でも、この惑星を超えた人生が本当にあるのだろうか？"
          }
        },
        "ID": "reaction_1"
      },
      {
        "Tag": "spring_movie_1",
        "Response": "love",
        "Whitelist": [],
        "SpecialResponses": {
          "BeforeMovie": {
            "ResponsePoint": null,
            "Script": "",
            "Text": "これは私の路地のすぐ上だよ...君は私がこれを愛するつもりだということを知ってるね。$h"
          },
          "DuringMovie": {
            "ResponsePoint": null,
            "Script": "/emote Demetrius 8/message Demetrius \"ディメトリウスはあごを掻いています...」",
            "Text": "技術的には、それは正しくないな... $3"
          },
          "AfterMovie": {
            "ResponsePoint": null,
            "Script": "",
            "Text": "まあ、彼らは間違いなくいくつかのことを飾ったが、それはまだほとんど正しいことだ！とにかく、楽しい時間を過ごしたよ。"
          }
        },
        "ID": "reaction_2"
      },
      {
        "Tag": "winter_movie_0",
        "Response": "dislike",
        "Whitelist": [],
        "SpecialResponses": {
          "BeforeMovie": {
            "ResponsePoint": null,
            "Script": "",
            "Text": "紙の中でこれについて読んでいます...私のためのものには見えなかったが。しかし私はそれに打撃を与えるつもりだ。"
          },
          "DuringMovie": null,
          "AfterMovie": {
            "ResponsePoint": null,
            "Script": "",
            "Text": "ナンセンス！それは全く科学的ではない！$4"
          }
        },
        "ID": "reaction_4"
      },
      {
        "Tag": "like",
        "Response": "like",
        "Whitelist": [],
        "SpecialResponses": {
          "BeforeMovie": {
            "ResponsePoint": null,
            "Script": "",
            "Text": "映画が悪くても、分析するのは面白い。"
          },
          "DuringMovie": null,
          "AfterMovie": {
            "ResponsePoint": null,
            "Script": "",
            "Text": "うーん...この映画の物語によって人間の動機のどの側面が満たされるのだろうか？$3"
          }
        },
        "ID": "reaction_3"
      }
    ]
  },
  {
    "NPCName": "Linus",
    "Reactions": [
      {
        "Tag": "spring_movie_1",
        "Response": "dislike",
        "Whitelist": [],
        "SpecialResponses": {
          "BeforeMovie": {
            "ResponsePoint": null,
            "Script": "",
            "Text": "私はここが場違いに感じるよ...誰も気にしないでほしい。$s"
          },
          "DuringMovie": {
            "ResponsePoint": null,
            "Script": "/emote Linus 28/message \"ライナスは床を見ています...」",
            "Text": ""
          },
          "AfterMovie": {
            "ResponsePoint": null,
            "Script": "",
            "Text": "君は自分でこういうことを経験することができるのに、なんでスクリーンをじっと見つめるんだ？$s"
          }
        },
        "ID": "reaction_1"
      },
      {
        "Tag": "*",
        "Response": "dislike",
        "Whitelist": [],
        "SpecialResponses": null,
        "ID": "reaction_0"
      },
      {
        "Tag": "dislike",
        "Response": "like",
        "Whitelist": [],
        "SpecialResponses": {
          "BeforeMovie": {
            "ResponsePoint": null,
            "Script": "",
            "Text": "ここは場違いだな...誰も気にしないでほしい。$s"
          },
          "DuringMovie": {
            "ResponsePoint": null,
            "Script": "/emote Linus 28/message \"ライナスは床を見ています...」",
            "Text": ""
          },
          "AfterMovie": {
            "ResponsePoint": null,
            "Script": "",
            "Text": "あまり刺激に慣れていないんだ...がっかりなゲストだったらすまない、@。オレを招待してくれてありがとう！"
          }
        },
        "ID": "reaction_2"
      }
    ]
  },
  {
    "NPCName": "Dwarf",
    "Reactions": [
      {
        "Tag": "*",
        "Response": "love",
        "Whitelist": [],
        "SpecialResponses": null,
        "ID": "reaction_0"
      },
      {
        "Tag": "love",
        "Response": "like",
        "Whitelist": [],
        "SpecialResponses": {
          "BeforeMovie": {
            "ResponsePoint": null,
            "Script": "",
            "Text": "ああっすごい！唯一の娯楽目的のために造られた宮殿だな！"
          },
          "DuringMovie": {
            "ResponsePoint": null,
            "Script": "/message \"ドワーフは憂鬱な状態のようです...」",
            "Text": ""
          },
          "AfterMovie": {
            "ResponsePoint": null,
            "Script": "",
            "Text": "オレは事を理解してなかった、だが閃光は魅惑的だったな！"
          }
        },
        "ID": "reaction_1"
      }
    ]
  },
  {
    "NPCName": "Marnie",
    "Reactions": [
      {
        "Tag": "winter_movie_0",
        "Response": "love",
        "Whitelist": [],
        "SpecialResponses": null,
        "ID": "reaction_0"
      },
      {
        "Tag": "love",
        "Response": "like",
        "Whitelist": [],
        "SpecialResponses": {
          "BeforeMovie": {
            "ResponsePoint": null,
            "Script": "",
            "Text": "この映画が好きになると思う！招待してくれて本当にありがとうな@。$h"
          },
          "DuringMovie": null,
          "AfterMovie": {
            "ResponsePoint": null,
            "Script": "",
            "Text": "ああ、家族が最後に無事だったことをとても嬉しく思うぞ。そして牛もな！$h"
          }
        },
        "ID": "reaction_1"
      },
      {
        "Tag": "like",
        "Response": "like",
        "Whitelist": [],
        "SpecialResponses": {
          "BeforeMovie": {
            "ResponsePoint": null,
            "Script": "",
            "Text": "映画ってのは、すごく気楽だな...何でも好きだよ！"
          },
          "DuringMovie": null,
          "AfterMovie": {
            "ResponsePoint": null,
            "Script": "",
            "Text": "素晴らしい時間が過ごせたぞ、@！オレのことを考えてくれてありがとう。"
          }
        },
        "ID": "reaction_2"
      }
    ]
  },
  {
    "NPCName": "Shane",
    "Reactions": [
      {
        "Tag": "summer_movie_0",
        "Response": "like",
        "Whitelist": [],
        "SpecialResponses": {
          "BeforeMovie": {
            "ResponsePoint": null,
            "Script": "",
            "Text": "ぶふ...あぁ、これは大丈夫だろうよ。（クンクン）（クンクン）...おやつが役に立つかもしれないな。"
          },
          "DuringMovie": {
            "ResponsePoint": "PK_villain",
            "Script": "",
            "Text": "オレは悪役を応援してる...（うっぷ）"
          },
          "AfterMovie": {
            "ResponsePoint": null,
            "Script": "",
            "Text": "オーケー、認めるよ...かなり良かったよ。"
          }
        },
        "ID": "reaction_4"
      },
      {
        "Tag": "spring_movie_0",
        "Response": "dislike",
        "Whitelist": [],
        "SpecialResponses": null,
        "ID": "reaction_0"
      },
      {
        "Tag": "classic",
        "Response": "dislike",
        "Whitelist": [],
        "SpecialResponses": null,
        "ID": "reaction_1"
      },
      {
        "Tag": "summer_movie_1",
        "Response": "love",
        "Whitelist": [],
        "SpecialResponses": null,
        "ID": "reaction_2"
      },
      {
        "Tag": "fall_movie_1",
        "Response": "love",
        "Whitelist": [],
        "SpecialResponses": null,
        "ID": "reaction_3"
      },
      {
        "Tag": "love",
        "Response": "like",
        "Whitelist": [],
        "SpecialResponses": {
          "BeforeMovie": {
            "ResponsePoint": null,
            "Script": "",
            "Text": "ヘヘ。実際にこれを見ることに興味があるんだ..."
          },
          "DuringMovie": {
            "ResponsePoint": null,
            "Script": "/message \"シェーンは笑わないようにしています」",
            "Text": "さて、これは良いね... $h"
          },
          "AfterMovie": {
            "ResponsePoint": null,
            "Script": "",
            "Text": "あなたが良い映画を見ているとき、他のすべてを忘れることができるよね...それはギフトだね。"
          }
        },
        "ID": "reaction_5"
      },
      {
        "Tag": "like",
        "Response": "like",
        "Whitelist": [],
        "SpecialResponses": {
          "BeforeMovie": {
            "ResponsePoint": null,
            "Script": "",
            "Text": "ぶふ...えぇ、これは大丈夫だと思うよ。（クンクン）（クンクン）...おやつが役に立つかもしれないね。"
          },
          "DuringMovie": null,
          "AfterMovie": {
            "ResponsePoint": null,
            "Script": "",
            "Text": "オーケー、認めるよ...かなり良かったね。"
          }
        },
        "ID": "reaction_6"
      },
      {
        "Tag": "dislike",
        "Response": "like",
        "Whitelist": [],
        "SpecialResponses": {
          "BeforeMovie": {
            "ResponsePoint": null,
            "Script": "",
            "Text": "うーん…これは痛みを伴うね。"
          },
          "DuringMovie": {
            "ResponsePoint": null,
            "Script": "/emote Shane 28/message \"シェーンは落ち込んでいます...」",
            "Text": ""
          },
          "AfterMovie": {
            "ResponsePoint": null,
            "Script": "",
            "Text": "私、落ち込んでる... $s"
          }
        },
        "ID": "reaction_7"
      }
    ]
  },
  {
    "NPCName": "Jas",
    "Reactions": [
      {
        "Tag": "horror",
        "Response": "dislike",
        "Whitelist": [],
        "SpecialResponses": null,
        "ID": "reaction_0"
      },
      {
        "Tag": "classic",
        "Response": "like",
        "Whitelist": [],
        "SpecialResponses": null,
        "ID": "reaction_1"
      },
      {
        "Tag": "*",
        "Response": "love",
        "Whitelist": [],
        "SpecialResponses": null,
        "ID": "reaction_2"
      },
      {
        "Tag": "love",
        "Response": "like",
        "Whitelist": [],
        "SpecialResponses": {
          "BeforeMovie": {
            "ResponsePoint": null,
            "Script": "",
            "Text": "映画を見て本当にハッピーよ！"
          },
          "DuringMovie": {
            "ResponsePoint": null,
            "Script": "/jump Jas/pause 400/playSound reward/message \"ジャスは恍惚としています！」",
            "Text": ""
          },
          "AfterMovie": {
            "ResponsePoint": null,
            "Script": "",
            "Text": "とてもたのしかったわ。つれてきてくれてありがとう！$h"
          }
        },
        "ID": "reaction_3"
      },
      {
        "Tag": "like",
        "Response": "like",
        "Whitelist": [],
        "SpecialResponses": {
          "BeforeMovie": {
            "ResponsePoint": null,
            "Script": "",
            "Text": "これは大人の映画だよね？大丈夫だと思う！"
          },
          "DuringMovie": {
            "ResponsePoint": null,
            "Script": "/message \"ジャスはうなずいて横からちらっと見ています。」",
            "Text": ""
          },
          "AfterMovie": {
            "ResponsePoint": null,
            "Script": "",
            "Text": "よかったね！それは...ええと...良い「ダイアログ」！...だよね？"
          }
        },
        "ID": "reaction_4"
      },
      {
        "Tag": "horror",
        "Response": "like",
        "Whitelist": [],
        "SpecialResponses": {
          "BeforeMovie": {
            "ResponsePoint": null,
            "Script": "",
            "Text": "わたし...わたしはこれを見ちゃダメなのかどうかわからない... $s"
          },
          "DuringMovie": {
            "ResponsePoint": null,
            "Script": "/shake Jas 250/pause 500/shake Jas 250/pause 500/emote Jas 28/message \"ジャスは震えています」",
            "Text": "怖い...$s"
          },
          "AfterMovie": {
            "ResponsePoint": null,
            "Script": "",
            "Text": "（クンクン）... $s"
          }
        },
        "ID": "reaction_5"
      }
    ]
  },
  {
    "NPCName": "Leah",
    "Reactions": [
      {
        "Tag": "spring_movie_1",
        "Response": "like",
        "Whitelist": [],
        "SpecialResponses": {
          "BeforeMovie": {
            "ResponsePoint": null,
            "Script": "",
            "Text": "本当にきれいな自然の絵があるってきいたの…本当に楽しみ！$h"
          },
          "DuringMovie": null,
          "AfterMovie": {
            "ResponsePoint": null,
            "Script": "",
            "Text": "すごく良かった。スターデューバレーの空中ショットで、わたしのキャビンを見たことだってあると確信してるの！$h"
          }
        },
        "ID": "reaction_4"
      },
      {
        "Tag": "art",
        "Response": "love",
        "Whitelist": [],
        "SpecialResponses": null,
        "ID": "reaction_0"
      },
      {
        "Tag": "classic",
        "Response": "like",
        "Whitelist": [],
        "SpecialResponses": null,
        "ID": "reaction_1"
      },
      {
        "Tag": "family",
        "Response": "like",
        "Whitelist": [],
        "SpecialResponses": null,
        "ID": "reaction_2"
      },
      {
        "Tag": "*",
        "Response": "dislike",
        "Whitelist": [],
        "SpecialResponses": null,
        "ID": "reaction_3"
      },
      {
        "Tag": "love",
        "Response": "like",
        "Whitelist": [],
        "SpecialResponses": {
          "BeforeMovie": {
            "ResponsePoint": null,
            "Script": "",
            "Text": "この映画は本当に興味深いね...私は不思議な人のための吸盤。"
          },
          "DuringMovie": null,
          "AfterMovie": {
            "ResponsePoint": null,
            "Script": "",
            "Text": "すごく良かったよ！話はすごくゆるいけど、それが頭じゃなくて感情に話すことを意図していたと思う。"
          }
        },
        "ID": "reaction_5"
      },
      {
        "Tag": "like",
        "Response": "like",
        "Whitelist": [],
        "SpecialResponses": {
          "BeforeMovie": {
            "ResponsePoint": null,
            "Script": "",
            "Text": "この映画に何を期待した方が良いか分からないけど、心を開いておくつもりだよ！"
          },
          "DuringMovie": null,
          "AfterMovie": {
            "ResponsePoint": null,
            "Script": "",
            "Text": "簡単だけど、良いね...映画の快適な食べ物のようなもの。"
          }
        },
        "ID": "reaction_6"
      },
      {
        "Tag": "dislike",
        "Response": "like",
        "Whitelist": [],
        "SpecialResponses": {
          "BeforeMovie": {
            "ResponsePoint": null,
            "Script": "",
            "Text": "映画のポスターが、かなり安っぽく見えるね。"
          },
          "DuringMovie": null,
          "AfterMovie": {
            "ResponsePoint": null,
            "Script": "",
            "Text": "それはちょっとしたことじゃなかったよね？"
          }
        },
        "ID": "reaction_7"
      }
    ]
  },
  {
    "NPCName": "Sandy",
    "Reactions": [
      {
        "Tag": "*",
        "Response": "love",
        "Whitelist": [],
        "SpecialResponses": null,
        "ID": "reaction_0"
      },
      {
        "Tag": "love",
        "Response": "like",
        "Whitelist": [],
        "SpecialResponses": {
          "BeforeMovie": {
            "ResponsePoint": null,
            "Script": "",
            "Text": "ペリカンタウンに来るための口実にすることがとてもうれしい！"
          },
          "DuringMovie": null,
          "AfterMovie": {
            "ResponsePoint": null,
            "Script": "",
            "Text": "とっても楽しかったわ、招待してくれてありがとう！もうすぐ帰った方がいいけど..."
          }
        },
        "ID": "reaction_1"
      }
    ]
  },
  {
    "NPCName": "Elliott",
    "Reactions": [
      {
        "Tag": "art",
        "Response": "love",
        "Whitelist": [],
        "SpecialResponses": null,
        "ID": "reaction_0"
      },
      {
        "Tag": "fall_movie_1",
        "Response": "dislike",
        "Whitelist": [],
        "SpecialResponses": null,
        "ID": "reaction_1"
      },
      {
        "Tag": "summer_movie_0",
        "Response": "dislike",
        "Whitelist": [],
        "SpecialResponses": null,
        "ID": "reaction_2"
      },
      {
        "Tag": "love",
        "Response": "like",
        "Whitelist": [],
        "SpecialResponses": {
          "BeforeMovie": {
            "ResponsePoint": null,
            "Script": "",
            "Text": "これが絶妙な夜だって予見してるの！"
          },
          "DuringMovie": null,
          "AfterMovie": {
            "ResponsePoint": null,
            "Script": "",
            "Text": "まるで自分の心が満たされているかのように感じる...映画のエネルギーが私に伝わったかな。すごい！"
          }
        },
        "ID": "reaction_3"
      },
      {
        "Tag": "like",
        "Response": "like",
        "Whitelist": [],
        "SpecialResponses": {
          "BeforeMovie": {
            "ResponsePoint": null,
            "Script": "",
            "Text": "この映画に関するすべての情報を避けてきました...完全な「盲目的」が好き！"
          },
          "DuringMovie": null,
          "AfterMovie": {
            "ResponsePoint": null,
            "Script": "",
            "Text": "すごく興味深い...しばらくそのことをよく考えるよ。"
          }
        },
        "ID": "reaction_4"
      },
      {
        "Tag": "dislike",
        "Response": "like",
        "Whitelist": [],
        "SpecialResponses": {
          "BeforeMovie": {
            "ResponsePoint": null,
            "Script": "",
            "Text": "これが楽しみっていうのはウソでしょ...$s"
          },
          "DuringMovie": null,
          "AfterMovie": {
            "ResponsePoint": null,
            "Script": "",
            "Text": "とても平凡だったね。そう思わない？"
          }
        },
        "ID": "reaction_5"
      }
    ]
  },
  {
    "NPCName": "Willy",
    "Reactions": [
      {
        "Tag": "like",
        "Response": "like",
        "Whitelist": [],
        "SpecialResponses": {
          "BeforeMovie": {
            "ResponsePoint": null,
            "Script": "",
            "Text": "ヘへ...無料の映画を断る理由は決してないでしょう！"
          },
          "DuringMovie": null,
          "AfterMovie": {
            "ResponsePoint": null,
            "Script": "",
            "Text": "ああ、それは私に、ol 'ポップスが言っていた物語を思い出させるよ..."
          }
        },
        "ID": "reaction_0"
      }
    ]
  },
  {
    "NPCName": "Leo",
    "Reactions": [
      {
        "Tag": "documentary",
        "Response": "love",
        "Whitelist": [],
        "SpecialResponses": null,
        "ID": "reaction_1"
      },
      {
        "Tag": "*",
        "Response": "like",
        "Whitelist": [],
        "SpecialResponses": null,
        "ID": "reaction_2"
      },
      {
        "Tag": "love",
        "Response": "like",
        "Whitelist": [],
        "SpecialResponses": {
          "BeforeMovie": {
            "ResponsePoint": null,
            "Script": "",
            "Text": "これを見たらワクワクしてきたよ…この世界のことは何でも勉強したいんだ！"
          },
          "DuringMovie": {
            "ResponsePoint": null,
            "Script": "/jump Leo/pause 400/playSound reward/message「レオは画面に釘付け！」",
            "Text": ""
          },
          "AfterMovie": {
            "ResponsePoint": null,
            "Script": "",
            "Text": "あれを見た？フェーン諸島を見せてくれた…ボクが居た場所だ！$h"
          }
        },
        "ID": "reaction_3"
      },
      {
        "Tag": "like",
        "Response": "like",
        "Whitelist": [],
        "SpecialResponses": {
          "BeforeMovie": {
            "ResponsePoint": null,
            "Script": "",
            "Text": "ここに来られて本当に嬉しいよ。ぜーんぶ面白いんだ！"
          },
          "DuringMovie": {
            "ResponsePoint": null,
            "Script": "/pause 500/emote Leo 32/message「レオは映画に興味津々のようです。」",
            "Text": ""
          },
          "AfterMovie": {
            "ResponsePoint": null,
            "Script": "",
            "Text": "ああ…魔法みたいだったね！"
          }
        },
        "ID": "reaction_4"
      }
    ]
  }
]